README.md
setup.py
iosense_connect/__init__.py
iosense_connect/data_access.py
iosense_connect.egg-info/PKG-INFO
iosense_connect.egg-info/SOURCES.txt
iosense_connect.egg-info/dependency_links.txt
iosense_connect.egg-info/requires.txt
iosense_connect.egg-info/top_level.txt