Metadata-Version: 2.1
Name: iosense-connect
Version: 4.0.7
Summary: iosense connect library
Home-page: UNKNOWN
Author: Faclon-Labs
Author-email: reachus@faclon.com
License: UNKNOWN
Platform: UNKNOWN
Classifier: Programming Language :: Python :: 3
Classifier: License :: OSI Approved :: MIT License
Classifier: Operating System :: OS Independent
